pi_gan_pytorch/__init__.py
pi_gan_pytorch/coordconv.py
pi_gan_pytorch/nerf.py
pi_gan_pytorch/pi_gan_pytorch.py
pi_gan_pytorch-0.0.11.dist-info/LICENSE
pi_gan_pytorch-0.0.11.dist-info/METADATA
pi_gan_pytorch-0.0.11.dist-info/WHEEL
pi_gan_pytorch-0.0.11.dist-info/top_level.txt
pi_gan_pytorch-0.0.11.dist-info/RECORD
