Metadata-Version: 2.1
Name: pi-gan-pytorch
Version: 0.0.11
Summary: π-GAN - Pytorch
Home-page: https://github.com/lucidrains/pi-gan-pytorch
Author: Phil Wang
Author-email: lucidrains@gmail.com
License: MIT
Keywords: artificial intelligence,generative adversarial network
Platform: UNKNOWN
Classifier: Development Status :: 4 - Beta
Classifier: Intended Audience :: Developers
Classifier: Topic :: Scientific/Engineering :: Artificial Intelligence
Classifier: License :: OSI Approved :: MIT License
Classifier: Programming Language :: Python :: 3.6
Requires-Dist: einops (>=0.3)
Requires-Dist: pillow
Requires-Dist: torch (>=1.6)
Requires-Dist: torchvision
Requires-Dist: tqdm
